LICENSE
README.md
setup.cfg
setup.py
algebra/__init__.py
algebra/__main__.py
algebra/utils.py
algebra/extractor/__init__.py
algebra/extractor/extractor.py
algebra/extractor/local_supremal.py
algebra/extractor/vis.py
algebra/lcs/__init__.py
algebra/lcs/edit_distance.py
algebra/lcs/lcs_graph.py
algebra/relations/__init__.py
algebra/relations/graph_based.py
algebra/relations/relation.py
algebra/relations/sequence_based.py
algebra/relations/supremal_based.py
algebra/relations/variant_based.py
algebra/variants/__init__.py
algebra/variants/parser.py
algebra/variants/variant.py
mutalyzer_algebra.egg-info/PKG-INFO
mutalyzer_algebra.egg-info/SOURCES.txt
mutalyzer_algebra.egg-info/dependency_links.txt
mutalyzer_algebra.egg-info/entry_points.txt
mutalyzer_algebra.egg-info/requires.txt
mutalyzer_algebra.egg-info/top_level.txt