Metadata-Version: 2.1
Name: mutalyzer-algebra
Version: 1.5.2
Summary: A Boolean Algebra for Genetic Variants
Home-page: https://github.com/mutalyzer/algebra
Author: Mark A. Santcroos, Jonathan K. Vis
Author-email: m.a.santcroos@lumc.nl, j.k.vis@lumc.nl
License: MIT
Keywords: algebra,genomics,graph,string,genetics,edit-distance,alignment,compare,sequence,variants,lcs,relations,hgvs,extractor
Classifier: Intended Audience :: Science/Research
Classifier: Intended Audience :: Developers
Classifier: Operating System :: OS Independent
Classifier: Programming Language :: Python :: 3
Classifier: Topic :: Scientific/Engineering :: Bio-Informatics
License-File: LICENSE
Provides-Extra: dev
Requires-Dist: coverage; extra == "dev"
Requires-Dist: flake8; extra == "dev"
Requires-Dist: pytest; extra == "dev"
Requires-Dist: setuptools; extra == "dev"
Requires-Dist: twine; extra == "dev"
